nanocompore/__init__.py
nanocompore/__main__.py
nanocompore/api.py
nanocompore/common.py
nanocompore/comparisons.py
nanocompore/config.py
nanocompore/database.py
nanocompore/eventalign_collapse.py
nanocompore/gof_tests.py
nanocompore/plotting.py
nanocompore/postprocessing.py
nanocompore/preprocessing.py
nanocompore/remora_wrapper.py
nanocompore/run.py
nanocompore/template_config.yaml
nanocompore/transcript.py
nanocompore/uncalled4.py
nanocompore/models/__init__.py
nanocompore/models/kmers_model_RNA_r9.4_180mv.tsv
nanocompore/models/rna002_5mer_levels_v1.txt
nanocompore/models/rna004_9mer_levels_v1.txt
nanocompore-2.0.0.dist-info/METADATA
nanocompore-2.0.0.dist-info/WHEEL
nanocompore-2.0.0.dist-info/entry_points.txt
nanocompore-2.0.0.dist-info/licenses/LICENSE
nanocompore-2.0.0.dist-info/RECORD
