Metadata-Version: 2.4
Name: nanocompore
Version: 2.0.0
Summary: Software package that identifies raw signal changes between two conditions from dRNA-Seq data.
Project-URL: repository, https://github.com/tleonardi/nanocompore
Project-URL: documentation, http://nanocompore.rna.rocks
Author-email: Mihail Zdravkov <mail@mzdravkov.com>, Logan Mulroney <lmulrone@soe.ucsc.edu>, Tommaso Leonardi <tom@itm6.xyz>, Adrien Leger <aleg@ebi.ac.uk>
License: GPL-3.0
License-File: LICENSE
Classifier: Development Status :: 4 - Beta
Classifier: Intended Audience :: Science/Research
Classifier: License :: OSI Approved :: GNU General Public License v3 (GPLv3)
Classifier: Programming Language :: Python :: 3
Classifier: Topic :: Scientific/Engineering :: Bio-Informatics
Requires-Python: <4.0,>=3.10
Requires-Dist: gmm-gpu>=0.2.5
Requires-Dist: gtfparse>=2.5.0
Requires-Dist: jaxtyping>=0.2.38
Requires-Dist: loguru<1.0,>=0.5
Requires-Dist: matplotlib<4.0,>=3.10
Requires-Dist: numpy<2.0
Requires-Dist: ont-remora==3.3
Requires-Dist: pandas<3.0,>=2.2
Requires-Dist: pod5<1.0.0,>=0.3.6
Requires-Dist: pyfaidx<1.0,>=0.8
Requires-Dist: pynvml<13.0.0,>=12.0.0
Requires-Dist: pysam<1.0.0,>=0.22.0
Requires-Dist: pyyaml<5.4,>=5
Requires-Dist: schema<1.0.0,>=0.7.5
Requires-Dist: scikit-learn<2.0,>=1.4
Requires-Dist: scipy<2.0,>=1.15
Requires-Dist: seaborn<1.0,>=0.13
Requires-Dist: statsmodels<1.0,>=0.14
Requires-Dist: tqdm<5,>=4
